{
  "0": {
    "day": "یکشنبه",
    "dhikr": "لا إلَهَ إلَّا اللهُ وَحدَهُ لا شَریکَ لَهُ، لَهُ المُلکُ وَلَهُ الحَمدُ، یُحیی وَیُمیتُ وَهُوَ عَلی کُلِّ شَیءٍ قَدیر"
  },
  "1": {
    "day": "دوشنبه",
    "dhikr": "اللّهُمَّ صَلِّ عَلی مُحَمَّدٍ وَآلِ مُحَمَّد"
  },
  "2": {
    "day": "سه‌شنبه",
    "dhikr": "أَستَغفِرُ اللهَ رَبِّی وَأَتوبُ إِلَیه"
  },
  "3": {
    "day": "چهارشنبه",
    "dhikr": "لا حَولَ وَلا قُوَّةَ إِلّا بِاللهِ العَلِیِّ العَظیم"
  },
  "4": {
    "day": "پنجشنبه",
    "dhikr": "اللّهُمَّ صَلِّ عَلی مُحَمَّدٍ وَآلِ مُحَمَّد"
  },
  "5": {
    "day": "جمعه",
    "dhikr": "اللّهُمَّ صَلِّ عَلی مُحَمَّدٍ وَآلِ مُحَمَّدٍ وَعَجِّل فَرَجَهُم"
  },
  "6": {
    "day": "شنبه",
    "dhikr": "سُبحانَ اللهِ وَبِحَمدِهِ، سُبحانَ اللهِ العَظیم"
  }
}
